{
    "@type": "Recipe",
    "aggregateRating": {
        "@type": "AggregateRating",
        "bestRating": {
            "@language": "en-US",
            "@value": "100"
        },
        "ratingCount": {
            "@language": "en-US",
            "@value": "5"
        },
        "ratingValue": {
            "@language": "en-US",
            "@value": "100"
        },
        "worstRating": {
            "@language": "en-US",
            "@value": "0"
        }
    },
    "image": {
        "@id": "https://kuharica.kontin.info/wp-content/uploads/2015/01/Lignje-s-kobasicama-i-kozicama-u-\u0161al\u0161i-od-raj\u010dice-darkova-web-kuharica-12.jpg"
    },
    "name": {
        "@language": "en-US",
        "@value": "Jadranska lignja i kozice na prigorski zimski na\u010din"
    },
    "recipeInstructions": {
        "@language": "en-US",
        "@value": "\n\t\t\t \tPro\u0161li mjesec, a slobodno sada ve\u0107 ka\u017eem i pro\u0161le godine :), imao sam priliku i \u010dast sudjelovati u prvom\u00a0Blogger Weekend Challangeu\u00a0u Hrvatskoj (moj fotke pogledajte ovdje) koji je bio organiziran od strane\u00a0LifeClass Terma Sveti Martin.\nSva tri dana koja smo tamo proveli meni su bila\u00a0za pam\u0107enje \u0161to zbog odli\u010dnog dru\u0161tva, savr\u0161enih doma\u0107ina, gastro ali i neizostavne vinske ponude kraja i jo\u0161 mnogih drugih stvari koje sam imao prilike vidjeti, okusiti i \u010duti. Ve\u0107 mi sad nedostaju vina vinske ku\u0107e Ha\u017ei\u0107 i sladoled od bu\u010dinog ulja iz restorana Mala Hi\u017ea. A da o desertima koje smo isprobali u\u00a0Gustolatou ne govorim.\n\nKako nisam neki putopisac, a stvarno \u017eelim s vama podijeliti svoju vikend avanturu u Me\u0111imurju,\u00a0predla\u017eem da skoknete i pro\u010ditate cijele vikend izvje\u0161taje na sljede\u0107im blogovima :):\n\nAndrea (Vo\u0107e i povr\u0107e)\nAnja (Sweethearts)\nIvana (\u0160minkerica)\nNikolina (Nicky\u2019s Bakes)\nTamara (Bite my cake)\nPersa (Beauty & Sweets)\n\nUz ve\u0107 navedene blogere uz nas su jo\u0161 bili Tihana,\u00a0Sa\u0161a, jo\u0161 jedan Sa\u0161a :),\u00a0Mateja\u00a0i\u00a0Tadeja\u00a0i ima da ih sve zapratite ako to ve\u0107 niste :).\nUz ovaj uvod savr\u0161eno ide i sljede\u0107i recept. Za\u0161to? Iz jednostavnog razloga jer sam dobio svje\u017ee lignje s Pa\u0161mana po povratku doma te sam ih odmah morao pripremiti :).\nDa se ne radi o standardnim lignjama u crvenom umaku dodao sam i malo kozica te malo svog Prigorja kroz jako ukusne kobasice i malo Gra\u0161evine.\nJelo iako je malo kompleksnije i ima u sebi vi\u0161e namirnica se zapravo lagano\u00a0priprema. Samo u odre\u0111enom vremenu dodajete odre\u0111ene namirnice i strpljivo \u010dekate da se sve samo skuha.\nNa kraju \u0107ete imati nezaboravnu gozbu koju \u0107ete htjeti brzo ponoviti. Zato prou\u010dite recept u nastavku i ako stignete po\u010dastite se ovim jelom ve\u0107 ovaj vikend.\n\nSastojci\n\nJadranska lignja \u2013 o\u010di\u0161\u0107ena (340 g)\nSvinjska kobasica za pe\u010denje (200 g)\nO\u010di\u0161\u0107eni repovi kozica (100 g)\n\u017duti luk (115 g)\nSvje\u017ea raj\u010dica (520 g)\nSvje\u017ei list bosiljka (5 kom)\nGra\u0161evina (1 dcl)\nPassat raj\u010dice (200 g)\nKrumpir (460 g)\nZelene masline (40 g)\nVoda (2 dcl)\nVrhnje\nLimun\nSvje\u017ei per\u0161in\nSlatka crvena paprika, papar, sol\n\nRecept\nIstisnite meso iz kobasica ili ih ogulite, a lignje nare\u017eite na kolutove (krakove ne usitnjavajte, posebno su efektni u jelu ako su cijeli).\nU wok ili duboku tavu bez dodavanja ulja na srednjoj vatri prepr\u017eite natrgano i usitnjeno meso kobasica dok ne poprimi sivkastu boju. Zatim dodajte sitno sjeckani luk i nekoliko listova svje\u017eeg bosiljka. Uz povremeno mije\u0161anje pri\u010dekajte da luk postane proziran.\nDodajte mljevenu slatku crvenu papriku te nakon kratkog pr\u017eenja\u00a0prelijte sve s 1 dcl Gra\u0161evine.\u00a0Dodajte zatim narezane svje\u017ee raj\u010dice te poklopite wok\u00a0da u njemu sve kuha oko 10 minuta dok raj\u010dice ne puste vodu. Nakon toga\u00a0dodajte lignje, passat raj\u010dicu, sol i papar po \u017eelji, promije\u0161ajte sve paze\u0107i da su vam lignje potopljene u teku\u0107ini te\u00a0ponovno poklopite wok i ostavite na laganoj vatri da se kuha dodatnih 60 minuta.\nNakon 60 minuta dodajte na male kockice narezani krumpir i repove kozica te kuhajte jelo dodatnih 30 minuta. Ako treba dodajte i malo vode kako bi sve namirnice bile stalno potopljene u teku\u0107ini. Provjerite slano\u0107u jela i dodajte soli ako treba u ovom trenutku.\nPrije nego ugasite plamen provjerite da li vam je krumpir dovoljno kuhan i ako nije kuhajte sve dok on ne bude gotov.\nLignje i kozice s kobasicama na kraju ukrasite svje\u017eim listovima per\u0161ina, narezanima maslinama te prelijte s laganim umakom od vrhnja i limunovog soka.\nDobar tek vam \u017eelim!\nPriprema lignji i kozica s kobasicama kroz fotografije\n           \nKako je vama ispalo?\nAndela Mokovic je prva isprobala lignje pripremiti s\u00a0kobasicama\u00a0i ka\u017ee da takva kombinacija fantasti\u010dna. Tako da nije samo do mene i da se samo meni svi\u0111a :). Evo kako je njezina ve\u010dera s lignjama izgledala.\n\nJadranska lignja i kozice na prigorski zimski na\u010din was last modified: March 3rd, 2015 by DarkoKontin\t\t\t\t"
    },
    "totalTime": {
        "@language": "en-US",
        "@value": "PT115M"
    },
    "@id": "http://example.org/recipe"
}