{
    "@type": "Recipe",
    "aggregateRating": {
        "@type": "AggregateRating",
        "bestRating": {
            "@language": "en-US",
            "@value": "5"
        },
        "ratingCount": {
            "@language": "en-US",
            "@value": "143"
        },
        "ratingValue": {
            "@language": "en-US",
            "@value": "4.69"
        },
        "worstRating": {
            "@language": "en-US",
            "@value": "1"
        }
    },
    "articleBody": {
        "@language": "en-US",
        "@value": "\nKenyan leaked sex tape  Sugar Daddy pulls over after shopping and roadhead to cum on my face 5. Math is hard, your penis is too! Models Online Now See All. \t\n\t\n\t\nNot a free member yet?\n     \t\nThe page you're trying to access: is not part of Pornhub. Two girls in mummy bondage  Most Subscribed."
    },
    "author": {
        "@language": "en-US",
        "@value": "admin"
    },
    "dateModified": {
        "@language": "en-US",
        "@value": "2019-06-05T16:34:42"
    },
    "datePublished": {
        "@language": "en-US",
        "@value": "2019-06-05T16:34:42+00:00"
    },
    "description": {
        "@language": "en-US",
        "@value": "\nYou are now viewing Redtube in English. Offering exclusive content not available on RedTube.    "
    },
    "mainEntityOfPage": {
        "@language": "en-US",
        "@value": "mummy porn video Kenya sugar"
    },
    "name": {
        "@language": "en-US",
        "@value": "mummy porn video Kenya sugar"
    },
    "publisher": {
        "@type": "Organization",
        "address": {
            "@language": "en-US",
            "@value": "http://avtonews.info"
        },
        "logo": {
            "@id": "_:Nb952657f2f4241c48999402b3d8303fb"
        },
        "name": {
            "@language": "en-US",
            "@value": "Adult"
        },
        "telephone": {
            "@language": "en-US",
            "@value": "Adult"
        }
    },
    "@id": "http://example.org/recipe"
}