{
    "@type": "Recipe",
    "aggregateRating": {
        "@type": "AggregateRating",
        "bestRating": {
            "@value": "5"
        },
        "ratingCount": {
            "@value": "143"
        },
        "ratingValue": {
            "@value": "4.69"
        },
        "worstRating": {
            "@value": "1"
        }
    },
    "articleBody": {
        "@value": "\nKristina A. They're not remotely as intimidating as they may look, and are really easy to pop in. Pathways to transformation.\t\n\t\t\nIntroduction\n     \t\nWhen you feel ready, insert more, using one hand to push the beads in and the other hand to keep your anus spread,\" she adds. Bret M. Any of the bleaching treatments outlined above can lead to scarring a."
    },
    "author": {
        "@value": "admin"
    },
    "dateModified": {
        "@value": "2019-02-12T04:33:30"
    },
    "datePublished": {
        "@value": "2019-02-12T04:33:30+00:00"
    },
    "description": {
        "@value": "\nRabia De Latour, M.    "
    },
    "mainEntityOfPage": {
        "@value": "models Our anal"
    },
    "name": {
        "@value": "models Our anal"
    },
    "publisher": {
        "@type": "Organization",
        "address": {
            "@value": "https://lis-utdanning.info"
        },
        "logo": {
            "@id": "_:N699ec749c18245759ea3f1440fd9b9c0"
        },
        "name": {
            "@value": "Adult"
        },
        "telephone": {
            "@value": "Adult"
        }
    },
    "@id": "http://example.org/recipe"
}