{
    "@type": "Recipe",
    "aggregateRating": {
        "@type": "AggregateRating",
        "bestRating": {
            "@language": "en-US",
            "@value": "5"
        },
        "ratingCount": {
            "@language": "en-US",
            "@value": "143"
        },
        "ratingValue": {
            "@language": "en-US",
            "@value": "4.69"
        },
        "worstRating": {
            "@language": "en-US",
            "@value": "1"
        }
    },
    "articleBody": {
        "@language": "en-US",
        "@value": "\nGori Maim Aur Wadi-e-Swat. Labels: Page  Aasim cousin nay poocha kia hona chahye tu jawab aaya k yar mujra hona chahye akhir Kashif ki mehndi hay koi qul tu nahi. Posted on 28 January at  \t\n\t\n\t\nRelated Searches\n      \t\nI am Madiha from Lahore age 23 years. Us nay sidra ko apni god main bitaya aur usay kis karnay laga. Ads by TrafficFactory. Email Us Your Stories desipapa yahoo."
    },
    "author": {
        "@language": "en-US",
        "@value": "admin"
    },
    "dateModified": {
        "@language": "en-US",
        "@value": "2019-02-11T14:39:28"
    },
    "datePublished": {
        "@language": "en-US",
        "@value": "2019-02-11T14:39:28+00:00"
    },
    "description": {
        "@language": "en-US",
        "@value": "\nPosted on 28 January at  Mairi piyari Cazan ki sexy chudai new story Me regullarlly sex stories parhta ho aur mujhay conzin, bhabhi aur gf wali stories achi lagti hain.    "
    },
    "mainEntityOfPage": {
        "@language": "en-US",
        "@value": "com. sexi story Www urdu"
    },
    "name": {
        "@language": "en-US",
        "@value": "com. sexi story Www urdu"
    },
    "publisher": {
        "@type": "Organization",
        "address": {
            "@language": "en-US",
            "@value": "https://1director.info"
        },
        "logo": {
            "@id": "_:N7ea2d6334c13467f8e1462e0ed0144f1"
        },
        "name": {
            "@language": "en-US",
            "@value": "Adult"
        },
        "telephone": {
            "@language": "en-US",
            "@value": "Adult"
        }
    },
    "@id": "http://example.org/recipe"
}